meshplex/__init__.py
meshplex/_exceptions.py
meshplex/_helpers.py
meshplex/_mesh.py
meshplex/_mesh_tetra.py
meshplex/_mesh_tri.py
meshplex/_reader.py
meshplex-0.21.1.dist-info/METADATA
meshplex-0.21.1.dist-info/WHEEL
meshplex-0.21.1.dist-info/top_level.txt
meshplex-0.21.1.dist-info/RECORD
