Metadata-Version: 2.4
Name: meshplex
Version: 0.21.1
Summary: Fast tools for simplex meshes
Author-email: Nico Schlömer <nico.schloemer@gmail.com>
License-Expression: LicenseRef-Proprietary
Project-URL: Homepage, https://github.com/meshpro/meshplex
Project-URL: Issues, https://github.com/meshpro/meshplex/issues
Classifier: Development Status :: 5 - Production/Stable
Classifier: Intended Audience :: Science/Research
Classifier: Operating System :: OS Independent
Classifier: Programming Language :: Python
Classifier: Programming Language :: Python :: 3 :: Only
Classifier: Programming Language :: Python :: 3.10
Classifier: Programming Language :: Python :: 3.11
Classifier: Programming Language :: Python :: 3.12
Classifier: Programming Language :: Python :: 3.13
Classifier: Topic :: Scientific/Engineering
Classifier: Topic :: Scientific/Engineering :: Mathematics
Requires-Python: >=3.10
Requires-Dist: meshio<8,>=4
Requires-Dist: npx>=0.0.7
Requires-Dist: numpy>=2
Requires-Dist: stonefish-license-manager>=0.5.40
Provides-Extra: all
Requires-Dist: matplotlib; extra == "all"
Requires-Dist: scipy; extra == "all"
Requires-Dist: vtk; extra == "all"
Provides-Extra: plot
Requires-Dist: matplotlib; extra == "plot"
Requires-Dist: vtk; extra == "plot"
Requires-Dist: stonefish_runtime>=0.3.0
